soccer/__init__.py
soccer/core.py
soccer/exceptions.py
soccer/soccer.py
soccer/util.py
soccer/data_connectors/__init__.py
soccer/data_connectors/data_connector.py
soccer/data_connectors/fdo_connector.py
soccer/data_connectors/sqlite_connector.py
soccer/data_connectors/tm_connector.py
soccer/tm/__init__.py
soccer/tm/items.py
soccer/tm/middlewares.py
soccer/tm/pipelines.py
soccer/tm/settings.py
soccer/tm/spiders/__init__.py
soccer/tm/spiders/tmcom.py
soccer/writers/__init__.py
soccer/writers/bootstrap_writer.py
soccer/writers/html_writer.py
soccer/writers/json_writer.py
soccer/writers/writer.py
soccer-0.0.2.dist-info/DESCRIPTION.rst
soccer-0.0.2.dist-info/METADATA
soccer-0.0.2.dist-info/RECORD
soccer-0.0.2.dist-info/WHEEL
soccer-0.0.2.dist-info/metadata.json
soccer-0.0.2.dist-info/top_level.txt
tests/__init__.py
tests/context.py
tests/test_local.py
tests/test_soccer.py
