Metadata-Version: 2.0
Name: soccer
Version: 0.0.2
Summary: A soccer data framework
Home-page: https://github.com/hhllcks/soccer
Author: Hendrik Hilleckes
Author-email: hhllcks@gmail.com
License: UNKNOWN
Platform: UNKNOWN
Classifier: Development Status :: 3 - Alpha
Classifier: Programming Language :: Python
Classifier: Programming Language :: Python :: 3 :: Only
Classifier: Programming Language :: Python :: 3.6
Requires-Dist: footballdataorg
